LICENSE
MANIFEST.in
pavement.py
paver-minilib.zip
setup.py
gogreen/__init__.py
gogreen/backdoor.py
gogreen/cache.py
gogreen/coro.py
gogreen/corocurl.py
gogreen/corofile.py
gogreen/corohttpd.py
gogreen/coromysql.py
gogreen/coromysqlerr.py
gogreen/coroqueue.py
gogreen/corowork.py
gogreen/coutil.py
gogreen/dqueue.py
gogreen/echo-coro.py
gogreen/emulate.py
gogreen/fileobject.py
gogreen/purepydns.py
gogreen/pyinfo.py
gogreen/sendfd.py
gogreen/statistics.py
gogreen/ultramini.py
gogreen.egg-info/PKG-INFO
gogreen.egg-info/SOURCES.txt
gogreen.egg-info/dependency_links.txt
gogreen.egg-info/top_level.txt